[
    {
        "id": "reverse",
        "type": "radio",
        "label": {
          "en": "Direction of motor rotation",
          "de": "Motordrehrichtung"
        },
        "value": "0",
        "values": [
          {
            "id": "0",
            "label": {
              "en": "Normal",
              "de": "Normal"
            }
          },
          {
            "id": "1",
            "label": {
              "en": "Inverse",
              "de": "Invers"
            }
          }
        ],
        "hint": {
          "en": "After changing the direction, the actor assumes it is at 0% / fully closed.",
          "de": "Nach der Richtungsänderung nimmt der Aktor an, dass er auf 0% / vollständig geschlossen ist."
        }
    },
    {
      "id": "movetime",
      "type": "number",
      "label": {
        "en": "Motor movement time",
        "de": "Bewegungszeit des Motors"
      },
      "value": 10,
      "min": 0,
      "max": 5000,
      "step": 0.1,
      "units": {
        "en": "Seconds",
        "de": "Sekunden"
      }
  },
  {
    "id": "calibration",
    "type": "radio",
    "label": {
      "en": "NO FUNCTION - Motor calibration",
      "de": "OHNE FUNKTION - Motorkalibrierung"
    },
    "value": "0",
    "values": [
      {
        "id": "0",
        "label": {
          "en": "Off"
        }
      },
      {
        "id": "1",
        "label": {
          "en": "On"
        }
      }
    ],
    "hint": {
      "en": "The motor must be completely retracted before activation! After activation, let the motor extend completely by pressing the 'open' button and stop it at the lower end position by pressing the 'close' button.",
      "de": "Der Motor muss vor der Aktivierung vollständig eingefahren sein! Nach der Aktivierung lassen Sie den Motor durch Drücken der 'öffnen'-Taste vollständig ausfahren und stoppen ihn in der unteren Endposition durch Drücken der 'schließen'-Taste."
    }
  }
]